peaks2utr/__init__.py
peaks2utr/__main__.py
peaks2utr/annotations.py
peaks2utr/collections.py
peaks2utr/constants.py
peaks2utr/criteria.py
peaks2utr/exceptions.py
peaks2utr/models.py
peaks2utr/postprocess.py
peaks2utr/preprocess.py
peaks2utr/utils.py
peaks2utr/validation.py
peaks2utr/demo/Tb927_01_v5.1.gff
peaks2utr/demo/Tb927_01_v5.1.slice.bam
peaks2utr-1.4.0.dist-info/METADATA
peaks2utr-1.4.0.dist-info/WHEEL
peaks2utr-1.4.0.dist-info/entry_points.txt
peaks2utr-1.4.0.dist-info/top_level.txt
peaks2utr-1.4.0.dist-info/RECORD
