Metadata-Version: 2.1
Name: peaks2utr
Version: 1.4.0
Summary: A robust, parallelized Python CLI for annotating three_prime_UTR
Home-page: https://github.com/haessar/peaks2utr
Author: William Haese-Hill
Author-email: william.haese-hill@glasgow.ac.uk
License: GNU General Public License v3 (GPLv3)
Classifier: Development Status :: 5 - Production/Stable
Classifier: Programming Language :: Python
Classifier: Programming Language :: Python :: 3.8
Classifier: Programming Language :: Python :: 3.9
Classifier: Programming Language :: Python :: 3.10
Classifier: Programming Language :: Python :: 3.11
Classifier: Programming Language :: Python :: 3 :: Only
Requires-Python: <3.12,>=3.8
Requires-Dist: requests
Requires-Dist: gffutils==0.12
Requires-Dist: pysam
Requires-Dist: MACS2==2.2.9.1
Requires-Dist: numpy<=1.26.4,>=1.21.4
Requires-Dist: tqdm
Requires-Dist: asgiref
Requires-Dist: psutil
Requires-Dist: pybedtools
Requires-Dist: typing-extensions
Requires-Dist: importlib-resources
Requires-Dist: zipp
